{
  "id":209,
  "text":
  [
  	"Vous vous cramponnez à la paroi rocheuse pendant toute la nuit. Le vent glacial vous cingle le visage et vous êtes saisi de tremblements incontrôlables, luttant de toutes vos forces pour ne pas vous évanouir. Vous perdez 2 points d'ENDURANCE. L'huile de Bakanal vous permet cependant de conserver suffisamment de chaleur dans votre corps pour arriver à survivre : sans elle, le froid aurait eu raison de vous."
  ],
  "battle": {},
  "info": "Attention vous venez de perdre 2 points d'endurance",
  "choice":[],
  "next_page":
  [
    {"id": 155, "text": "Rendez-vous au "}
  ]
}